examples/__init__.py
examples/api/__init__.py
examples/api/coinbase.py
examples/api/crypto.py
examples/models/__init__.py
examples/models/user.py
sd_utils/__init__.py
sd_utils/func.py
sd_utils/logger.py
sd_utils/api/__init__.py
sd_utils/api/client.py
sd_utils/api/endpoint.py
sd_utils/api/error.py
sd_utils/api/provider.py
sd_utils/api/rate_limit.py
sd_utils/api/request.py
sd_utils/api/service.py
sd_utils/api/impl/__init__.py
sd_utils/api/impl/flask.py
sd_utils/github/__init__.py
sd_utils/github/fileio.py
sd_utils/github_actions/__init__.py
sd_utils/github_actions/action.py
sd_utils/models/__init__.py
sd_utils/models/field.py
sd_utils/models/model.py
sd_utils/plugins/__init__.py
sd_utils/plugins/plugin_base.py
sd_utils/plugins/plugin_collector.py
sd_utils/plugins/plugin_manager.py
sd_utils-0.6.0.dist-info/LICENSE
sd_utils-0.6.0.dist-info/METADATA
sd_utils-0.6.0.dist-info/WHEEL
sd_utils-0.6.0.dist-info/top_level.txt
sd_utils-0.6.0.dist-info/RECORD
