Metadata-Version: 2.1
Name: sd-utils
Version: 0.6.0
Summary: A python module with basic utils I tend to use in my projects
Home-page: https://github.com/stephend017/sd_utils
Author: Stephen Davis
Author-email: stephenedavis17@gmail.com
License: UNKNOWN
Platform: UNKNOWN
Classifier: Programming Language :: Python :: 3
Classifier: License :: OSI Approved :: MIT License
Classifier: Operating System :: OS Independent
Requires-Dist: pygithub
Requires-Dist: pyyaml
Requires-Dist: flask
